pulumi_kubernetes/__init__.py
pulumi_kubernetes/_inputs.py
pulumi_kubernetes/_tables.py
pulumi_kubernetes/_utilities.py
pulumi_kubernetes/outputs.py
pulumi_kubernetes/provider.py
pulumi_kubernetes/pulumi-plugin.json
pulumi_kubernetes/py.typed
pulumi_kubernetes/admissionregistration/__init__.py
pulumi_kubernetes/admissionregistration/v1/MutatingWebhookConfiguration.py
pulumi_kubernetes/admissionregistration/v1/MutatingWebhookConfigurationList.py
pulumi_kubernetes/admissionregistration/v1/MutatingWebhookConfigurationPatch.py
pulumi_kubernetes/admissionregistration/v1/ValidatingAdmissionPolicy.py
pulumi_kubernetes/admissionregistration/v1/ValidatingAdmissionPolicyBinding.py
pulumi_kubernetes/admissionregistration/v1/ValidatingAdmissionPolicyBindingList.py
pulumi_kubernetes/admissionregistration/v1/ValidatingAdmissionPolicyBindingPatch.py
pulumi_kubernetes/admissionregistration/v1/ValidatingAdmissionPolicyList.py
pulumi_kubernetes/admissionregistration/v1/ValidatingAdmissionPolicyPatch.py
pulumi_kubernetes/admissionregistration/v1/ValidatingWebhookConfiguration.py
pulumi_kubernetes/admissionregistration/v1/ValidatingWebhookConfigurationList.py
pulumi_kubernetes/admissionregistration/v1/ValidatingWebhookConfigurationPatch.py
pulumi_kubernetes/admissionregistration/v1/__init__.py
pulumi_kubernetes/admissionregistration/v1/_inputs.py
pulumi_kubernetes/admissionregistration/v1/outputs.py
pulumi_kubernetes/admissionregistration/v1alpha1/MutatingAdmissionPolicy.py
pulumi_kubernetes/admissionregistration/v1alpha1/MutatingAdmissionPolicyBinding.py
pulumi_kubernetes/admissionregistration/v1alpha1/MutatingAdmissionPolicyBindingList.py
pulumi_kubernetes/admissionregistration/v1alpha1/MutatingAdmissionPolicyBindingPatch.py
pulumi_kubernetes/admissionregistration/v1alpha1/MutatingAdmissionPolicyList.py
pulumi_kubernetes/admissionregistration/v1alpha1/MutatingAdmissionPolicyPatch.py
pulumi_kubernetes/admissionregistration/v1alpha1/ValidatingAdmissionPolicy.py
pulumi_kubernetes-4.24.0.dist-info/METADATA
pulumi_kubernetes-4.24.0.dist-info/WHEEL
pulumi_kubernetes-4.24.0.dist-info/top_level.txt
pulumi_kubernetes-4.24.0.dist-info/RECORD
